seafileapi/__init__.py
seafileapi/admin.py
seafileapi/client.py
seafileapi/exceptions.py
seafileapi/files.py
seafileapi/group.py
seafileapi/repo.py
seafileapi/repos.py
seafileapi/utils.py
tests/__init__.py
tests/conftest.py
tests/fixtures.py
tests/test_files.py
tests/test_repos.py
tests/utils.py
python_seafile_api-0.2.3.dist-info/LICENSE
python_seafile_api-0.2.3.dist-info/METADATA
python_seafile_api-0.2.3.dist-info/WHEEL
python_seafile_api-0.2.3.dist-info/top_level.txt
python_seafile_api-0.2.3.dist-info/RECORD
